flow_cli/__init__.py
flow_cli/main.py
flow_pubsub_cli-0.1.2.dist-info/LICENSE
flow_pubsub_cli-0.1.2.dist-info/METADATA
flow_pubsub_cli-0.1.2.dist-info/WHEEL
flow_pubsub_cli-0.1.2.dist-info/entry_points.txt
flow_pubsub_cli-0.1.2.dist-info/top_level.txt
flow_pubsub_cli-0.1.2.dist-info/RECORD
