Metadata-Version: 2.2
Name: flow-pubsub-cli
Version: 0.1.2
Summary: A command-line client for SuperCortex Flow - a privacy-preserving, decentralized pub/sub messaging system
Home-page: https://github.com/igutekunst/flow
Author: SuperCortex Flow
Author-email: isaac@supercortex.io
License: MIT
Project-URL: Bug Tracker, https://github.com/igutekunst/flow/issues
Project-URL: PyPI, https://pypi.org/project/flow-pubsub-cli/
Project-URL: Documentation, https://github.com/igutekunst/flow#readme
Keywords: pubsub,messaging,decentralized,privacy,cli,websockets,cryptography,distributed-systems
Classifier: Development Status :: 3 - Alpha
Classifier: Intended Audience :: Developers
Classifier: Intended Audience :: System Administrators
Classifier: License :: OSI Approved :: MIT License
Classifier: Operating System :: OS Independent
Classifier: Programming Language :: Python :: 3
Classifier: Programming Language :: Python :: 3.8
Classifier: Programming Language :: Python :: 3.9
Classifier: Programming Language :: Python :: 3.10
Classifier: Programming Language :: Python :: 3.11
Classifier: Programming Language :: Python :: 3.12
Classifier: Topic :: Communications
Classifier: Topic :: System :: Distributed Computing
Classifier: Topic :: Software Development :: Libraries :: Python Modules
Classifier: Topic :: Internet
Classifier: Topic :: Security :: Cryptography
Requires-Python: >=3.8
License-File: LICENSE
Requires-Dist: click>=8.1.0
Requires-Dist: requests>=2.31.0
Requires-Dist: websockets>=12.0
Dynamic: author
Dynamic: author-email
Dynamic: classifier
Dynamic: description
Dynamic: description-content-type
Dynamic: home-page
Dynamic: keywords
Dynamic: license
Dynamic: project-url
Dynamic: requires-dist
Dynamic: requires-python
Dynamic: summary
